{
    "@class": "com.kony.gen.viz.model.component.KVizLabel",
    "DNDConfig": null,
    "__parentReadjusting__": false,
    "_height_": {
        "type": "ref",
        "value": "preferred"
    },
    "_left_": {
        "type": "string",
        "value": "121dp"
    },
    "_margin_": [
        1,
        1,
        1,
        1
    ],
    "_padding_": [
        0,
        0,
        0,
        0
    ],
    "_skin_": "sba48e84c7324c62bca439f27adfbd1f",
    "_text_": "DEmo",
    "_top_": {
        "type": "string",
        "value": "75dp"
    },
    "_width_": {
        "type": "ref",
        "value": "preferred"
    },
    "_wrapping_": 2,
    "android": {
        "textStyle": {
            "letterSpacing": 0,
            "strikeThrough": false
        }
    },
    "canUpdateUI": true,
    "containerweight": 100,
    "contentalignment": 4,
    "id": "lbldemo",
    "info": null,
    "ipad": {
        "psp": {
            "wrapping": 2
        }
    },
    "iphone": {
        "psp": {
            "wrapping": 2
        }
    },
    "iscustomlayout": false,
    "isvisible": true,
    "kuid": "fcac52e9699e4a7dac18ff4d56e83f7a",
    "name": "kony.ui.Label",
    "parent": "Form1",
    "pf": "Form1",
    "retaincontentalignment": false,
    "retainflexpositionproperties": false,
    "textstyle": {},
    "tooltip": "",
    "wType": "Label",
    "zindex": 1
}